setup.py
rtplanchecking/init.py
rtplanchecking/pull_mephisto.py
rtplanchecking/scatter_factors.py
rtplanchecking/utilities.py
rtplanchecking.egg-info/PKG-INFO
rtplanchecking.egg-info/SOURCES.txt
rtplanchecking.egg-info/dependency_links.txt
rtplanchecking.egg-info/top_level.txt