Metadata-Version: 1.0
Name: rtplanchecking
Version: 0.1
Summary: Checks patient plans
Home-page: UNKNOWN
Author: Simon Biggs
Author-email: mail@simonbiggs.net
License: AGPL3+
Platform: UNKNOWN
